Workbook

Sheet 📋 Collecte Entretiens
A1: CARTOGRAPHIE DES OUTILS IT – CHANTIER BOUYGUES CONSTRUCTION
A3: N° | B3: Date Entretien | C3: Service / Département | D3: Interlocuteur | E3: FLUX | F3: Nature | G3: Nom de l'Outil | H3: Usage / Pourquoi | I3: Interne / Externe | J3: Éditeur / Fournisseur | K3: Alimentation (Manuel/Auto) | L3: Fréquence d'utilisation | M3: Alimenté par qui | N3: Alimente quel outil | O3: Interfaces / Connexions | P3: Niveau Maturité | Q3: Commentaires / Points d'attention | R3: Colonne32
A4: =ROW()-3 -> 1 | B4: 46169 | C4: Direction | D4: Julie | E4: GESTION DES ST | F4: Socle de données | G4: BATIS | H4: Declaration des ST(paiement direct) | I4: Externe | J4: Tisseo | K4: Manuel | L4: Quotidien | M4: Alimenté par Julie, les sous traitants, tisseo, m.o, attestation légal (connecté en temps réel) | N4: Aucun | O4: 4 – Optimisé | P4: Assez mature maintenant | Q4: NA
A5: =ROW()-3 -> 2 | B5: 46169 | C5: Direction | D5: Julie | E5: CIRCUIT DE VALIDATION | F5: Application métiers | G5: E-paraph | H5: Circuit de validation en interne avant signature | I5: Interne | J5: E-paraph | K5: Manuel | L5: Quotidien | M5: Tout le monde | N5: Aucun | O5: 3 – Mature | P5: Mature | Q5: Manque d'ergonomie sur le tab de co (quel ST concerné + Numéro contrat) | R5: Application métiers | W5: Application métiers
A6: =ROW()-3 -> 3 | B6: 46169 | C6: Direction | D6: Julie | E6: CIRCUIT DE VALIDATION | F6: Application métiers | G6: Docusign | I6: Externe | J6: Docusign | K6: Manuel | L6: Quotidien | N6: Aucun | O6: 3 – Mature | P6: Mature | W6: Socle de données
A7: =ROW()-3 -> 4 | B7: 46169 | C7: Direction | D7: Julie | E7: N.A | F7: Application métiers | G7: CWT | H7: Plateforme de voyage adapté à la politique voyage de Bouygues | I7: Externe | J7: CWT EUROPE | K7: Manuel | L7: Hebdomadaire | M7: Julie alimente au niveau de la resa, après il y a un circuit de validation(envoyé à un supérieur hiérarchique)=> politique voyage | N7: Relier à un autre logica bouyguesiel de compt | O7: 3 – Mature | P7: Mature | W7: Application métiers/Socle de donnée
A8: =ROW()-3 -> 5 | B8: 46169 | C8: Direction | D8: Julie | E8: N.A | F8: Application métiers | G8: Tableau | H8: Commande traiteur | I8: Externe | J8: Microsoft | K8: Manuel | L8: Ponctuel | N8: Aucun | O8: 3 – Mature | P8: Mature
A9: =ROW()-3 -> 6 | B9: 46169 | C9: Direction | D9: Julie | E9: GESTION DES MATÉRIELS | F9: Application métiers | G9: Oasis | H9: Déclaration d'incidents | I9: Interne | J9: Microsoft | K9: Manuel | L9: Ponctuel | M9: Tout le monde (Bouygues) | N9: Aucun | O9: 3 – Mature | P9: Mature
A10: =ROW()-3 -> 7 | B10: 46169 | C10: Direction | D10: Julie | E10: GESTION DES CONTRATS | F10: Application métiers | G10: Excel | H10: Contrats avenant, ordre de service, courrier | I10: Externe | J10: Microsoft | K10: Manuel | N10: Sharepoint | O10: 3 – Mature | P10: Mature
A11: =ROW()-3 -> 8 | B11: 46169 | C11: Direction | D11: Julie | E11: N.A | F11: Application métiers | G11: Word | H11: Courrier | I11: Externe | J11: Microsoft | K11: Manuel | L11: Ponctuel | N11: Aucun | O11: 3 – Mature | P11: Mature
A12: =ROW()-3 -> 9 | B12: 46169 | C12: Direction | D12: Julie | E12: GESTION DES ST | F12: Application métiers | G12: E-checking | H12: Pour les entreprises, Julie créer l'acces de l'entreprise(ST, prestataire ) | I12: Externe | J12: BYCN | K12: Manuel | L12: Ponctuel | M12: Julie, Valérie | N12: Aucun | O12: 1 – Basique | P12: Mature
A13: =ROW()-3 -> 10 | B13: 46170 | C13: Qualité | D13: Alexandre | E13: Contrôle Qualité | F13: Socle de données | G13: Quickconnect | H13: Workflow de contrôle qualité bétonnage, eprouvettes, accueil sécurité, formation post travail | I13: Interne | J13: Synologie | K13: Manuel | L13: Quotidien | M13: Tout le monde(travaux, prestatire, sous traitants, | N13: Sharepoint | O13: Connexion avec les mails et le sharepoint doe(dossier d'ouvrages éxécuté), prestataires externes (Sgma Beton) => pas fluide | P13: Pas mature => plein de bug, niveau connexion ok, | Q13: Constistution du Doe => via le workflow => fiche de contrôle(defintion des points d'arrets, plan de contrôle , deversement sur le sharepoint, verification par les conducteurs de travaux)
A14: =ROW()-3 -> 11 | B14: 46170 | C14: Qualité | D14: Alexandre | E14: Commande de matériel | F14: Socle de données | G14: Pablo | H14: Acheter du matériel | I14: Interne | J14: Systra | K14: Manuel | L14: Mensuel | M14: Tout le monde(travaux, prestatire, sous traitants, | N14: HARMONIE | O14: Mature
A15: =ROW()-3 -> 12 | B15: 46170 | C15: Qualité | D15: Alexandre | E15: Contrôle Qualité (visualisation) | F15: Application métiers | G15: Cabine de pilotage(Power BI) | H15: Pas utilisé | I15: Interne | J15: BYCN | K15: Automatique | L15: Ponctuel | N15: Aucun | O15: BYCN(sharepoint) | Q15: Outils sous exploité => indicateur de suivi
A16: =ROW()-3 -> 13 | B16: 46170 | C16: Qualité | D16: Alexandre | E16: Contrôle Qualité | F16: Application métiers | G16: Excel | H16: TCD | I16: Externe | J16: Microsoft | K16: Manuel | L16: Regulierement | M16: Alexandre | N16: Aucun
A17: =ROW()-3 -> 14 | B17: 46170 | C17: Qualité | D17: Alexandre | E17: MAD | F17: Application métiers | G17: IDCAPTURE | H17: Lever de reserve(mis à disposition pour les prochain prestataire, code couleur, visuel plus parlant , suivi dans le temps, position dans l'espace ) | I17: Externe | J17: IDCAPTURE | K17: Manuel | L17: Quotidien | M17: Equipe travaux, Qualité, MOE | N17: Aucun | O17: Alexandre admin, met en place les comptes utilisateur | P17: 3 – Mature
A18: =ROW()-3 -> 15 | B18: 46170 | C18: Qualité | D18: Alexandre | E18: Contrôle Qualité | F18: Socle de données | G18: Mezzoteam | H18: Gestion documentaires | I18: Externe | J18: MEZZOTEAM | K18: Manuel/Automatique | L18: Hebdomadaire | M18: Methode, Environnement, toutes les équipes mené à réalisé des documents | N18: Aucun | O18: Fluide | P18: Mature | Q18: Differentes partie prenantes, contrôle en interne de la conformité des doculents puis par la MOE qui emet ou pas un visa(refusé, commentaire, accepté) => pour les DAF (demande agrégation produit
A19: =ROW()-3 -> 16 | B19: 46170 | C19: Méthode/BIM | D19: Etienne | E19: GESTION DE MAQUETTES | F19: Socle de données | G19: Trimbleconnect | H19: Déposer les maquettes (sharepoint des maquettes) | I19: Externe | J19: tekla bimsight(licence) | K19: Manuel | L19: Tous les jours | M19: BE, Méthodes, | N19: Aucun | O19: Fluide | P19: Mature | Q19: 70 maquetttes généré par les bureau d'étude
A20: =ROW()-3 -> 17 | B20: 46170 | C20: Méthode/BIM | D20: Etienne | E20: PRODUCTION DE MAQUETTES | F20: Application métiers | G20: Revit | H20: Produire les maquettes(3D) | I20: Externe | J20: Autodesk(coût:système token) | K20: Manuel | L20: Tous les jours | M20: Méthode, BIM | N20: Aucun | O20: Fluide | P20: En developpement
B21: 46170 | C21: Méthode/BIM | D21: Etienne | E21: GESTION DE MAQUETTES | F21: Application métiers | G21: Sofistik bridge | H21: Modéliser la maquettes que pour le tunnel | I21: Externe | J21: Autodesk | K21: Manuel | L21: Ponctuel | M21: BIM | N21: Aucun | O21: Fluide
A22: =ROW()-3 -> 19 | B22: 46170 | C22: Méthode/BIM | D22: Etienne | E22: PRODUCTION DE MAQUETTES | F22: Application métiers | G22: Autocad | H22: Plan (production)=> 2D | I22: Externe | J22: Autodesk | K22: Manuel | L22: Tous les jours | M22: Méthode, BIM | N22: Aucun | O22: Fluide | P22: Mature
A23: =ROW()-3 -> 20 | B23: 46170 | C23: Méthode/BIM | D23: Etienne | E23: GESTION DE MAQUETTES | F23: Application métiers | G23: Inventor | H23: 3D => pièce mécanique | I23: Externe | J23: Autodesk | K23: Manuel | L23: Ponctuel | M23: Méthode, BIM | N23: Aucun | O23: Fluide | P23: Mature
A24: =ROW()-3 -> 21 | B24: 46170 | C24: Méthode/BIM | D24: Etienne | E24: PRODUCTION DE MAQUETTES | F24: Application métiers | G24: Civil 3D | H24: Dessein du terrassement | I24: Externe | J24: Autodesk | K24: Manuel | L24: Ponctuel | M24: Méthode, BIM | N24: Aucun | O24: Fluide | P24: Mature | Q24: Dépend du contexte et de l'objet à modéliser
A25: =ROW()-3 -> 22 | B25: 46170 | C25: Méthode/BIM | D25: Etienne | E25: GESTION DE MAQUETTES | F25: Application métiers | G25: Simple BIM | H25: Fusionnage de maquettes | I25: Externe | J25: Licence | K25: Manuel | L25: Hebdomadaire | M25: Etienne | N25: Aucun | O25: Fluide | P25: Mature
A26: =ROW()-3 -> 23 | B26: 46170 | C26: Méthode/BIM | D26: Etienne | E26: GESTION DE MAQUETTES | F26: Application métiers | G26: BIM vision | H26: Ouvrir une maquette | I26: Externe | J26: Technologia BIM | K26: Manuel | L26: Quotidien | M26: Lucas, Etienne, equipes travaux | N26: Aucun | O26: Fluide | P26: Mature
A27: =ROW()-3 -> 24 | B27: 46170 | C27: Méthode/BIM | D27: Etienne | E27: GESTION DE MAQUETTES | F27: Application métiers | G27: QGIS | H27: SIG, repère dans un plan | I27: Externe | J27: QGIS | K27: Manuel | L27: Ponctuel | M27: Topo, Directeur technique, pixis | N27: Aucun | O27: Pixis | P27: Mature
A28: =ROW()-3 -> 25 | B28: 46170 | C28: Méthode/BIM | D28: Etienne | E28: GESTION DE MAQUETTES | F28: Application métiers | G28: Anaconda | H28: Code | I28: Externe | K28: Manuel | L28: Ponctuel | M28: Etienne | N28: Aucun | P28: Mature
A29: =ROW()-3 -> 26 | B29: 46170 | C29: Méthode/BIM | D29: Etienne | E29: GESTION DE MAQUETTES | F29: Socle de données | G29: Mezzoteam | H29: Gestion documentaires | I29: Externe | J29: MEZZOTEAM | K29: Manuel/Automatique | L29: Hebdomadaire | M29: Methode, Environnement, toutes les équipes mené à réalisé des documents | N29: Aucun | O29: Fluide | P29: Mature | Q29: Differentes partie prenantes, contrôle en interne de la conformité des doculents puis par la MOE qui emet ou pas un visa(refusé, commentaire, accepté) => pour les DAF (demande agrégation produit
A30: =ROW()-3 -> 27 | B30: 46171 | C30: Contrat Manager | D30: Martin | E30: GESTION DES ENCAISSEMENTS | F30: Socle de données | G30: Excel | H30: Suivi des recettes et des montants cumulés , mesnuel => situation de travaux | I30: Externe | J30: Microsoft | K30: Manuel | L30: Tous les mois | M30: Tout le monde | N30: Aucun
A31: =ROW()-3 -> 28 | B31: 46171 | C31: Contrat Manager | D31: Martin | E31: GESTION DES ENCAISSEMENTS | F31: Application métiers | G31: E-project | H31: Permet d'activer la facturation , voir la situation | J31: Tisseo | K31: Manuel | L31: Ponctuel | N31: Martin | P31: En developpement
A32: =ROW()-3 -> 29 | B32: 46171 | C32: Contrat Manager | D32: Martin | E32: AVANCEMENTS JALON CHANTIER | F32: Application métiers | G32: Word | H32: Avancement avec les ingé | I32: Externe | J32: Microsoft | K32: Manuel | L32: Ponctuel | M32: Tout le monde | N32: Aucun
A33: =ROW()-3 -> 30 | B33: 46171 | C33: Contrat Manager | D33: Martin | E33: FACTURATION PARTENAIRE | F33: Application métiers | G33: Baseware | H33: Validé les facturations partenaires, | I33: Interne | J33: Soletanche | K33: Manuel | L33: Hebdomadaire | M33: Equipe de Gestion | N33: Harmonie | O33: Interne | P33: Mature
A34: =ROW()-3 -> 31 | B34: 46171 | C34: Contrat Manager | D34: Thierry | E34: GESTION DE CONTRATS | F34: Application métiers | G34: NotebookLM | H34: Redaction de document, mémoire, reclamation | I34: Interne | J34: GOOGLE | K34: Manuel | L34: Quotidien | M34: Thierry | N34: Aucun | P34: Mature
A35: =ROW()-3 -> 32 | B35: 46171 | C35: Contrat Manager | D35: Thierry | E35: GESTION DE CONTRATS | F35: Socle de données | G35: Sharepoint | H35: Accès aux documents | I35: Externe | J35: MICROSOFT | K35: Manuel | L35: Hebdomadaire | M35: Tous les services
A36: =ROW()-3 -> 33 | B36: 46171 | C36: Contrat Manager | D36: Thierry | E36: GESTION DE CONTRATS | F36: Socle de données | G36: Excel | I36: Externe | J36: MICROSOFT | K36: Manuel | L36: Hebdomadaire | M36: Tous les services | N36: Tous
A37: =ROW()-3 -> 34 | B37: 46171 | C37: Contrat Manager | D37: Thierry | E37: GESTION DE CONTRATS | F37: Application métiers | G37: Cabine de pilotage(Power BI) | H37: Suivi du pilotage/ avancement des chantiers | I37: Interne | J37: MICROSOFT | K37: Automatique | L37: Hebdomadaire | M37: Equipe travaux | O37: Excel | P37: Mature | Q37: (Power BI Miles stones management system )
A38: =ROW()-3 -> 35 | B38: 46190 | C38: Direction | D38: Morgan | E38: CIRCUIT DE VALIDATION | F38: Application métiers | G38: Baseware | H38: Validation | K38: Manuel
A39: =ROW()-3 -> 36 | B39: 46175 | C39: Comptabilité/gestion | D39: Abdellah | E39: ENGAGEMENT DES DÉPENSES | F39: Socle de données | G39: Harmony | H39: Engagements des dépenses à la reception des bl, suivre les commandes , envoi des avis de paiement, Pour les ST=> création d'un b.D.C=> basé sur la taille du contrat => situation mise à jour | I39: Interne | K39: Manuel | L39: Quotidien | M39: Pablo commande passé par les opérationneles trier par ateliers, Baseware | N39: Baseware | P39: Mature | Q39: Abdellah commence à engagé des dépenses par la reception des bl => une fois recpetionné transfert dans la PC100 => PAMS peut par la suite commencé le CB / Si litige => notation la différence de montant et enregistrement de la facture dans le PC100 => paiement du montant "légitime"=> discussion avec le fournisseur => génération d'un avoir ou paiement de la totalité
A40: =ROW()-3 -> 37 | B40: 46175 | C40: Comptabilité/gestion | D40: Abdellah | E40: GESTION DE FACTURATION | F40: Application métiers/Socle de donnée | G40: Excel | H40: Chronofacture, BDD factures, rapprochement entre la proposition d'ADF envoyé par SIHEM et les factures présents dans le BDD, envoie de la PC100 | I40: Interne | J40: Microsoft | K40: Manuel | L40: Tous les jours | M40: Équipe AGC | N40: Tout | P40: Mature
A41: =ROW()-3 -> 38 | B41: 46175 | C41: Comptabilité/gestion | D41: Abdellah | E41: GESTION DE FACTURATION | F41: Application métiers | G41: Docusign | H41: Notification d'un nouveau contrats | I41: Externe | K41: Automatique | L41: Hebdomadaire | M41: Membres d'une boucle de validation | N41: Tout
A42: =ROW()-3 -> 39 | B42: 46175 | C42: Comptabilité/gestion | D42: Abdellah | E42: GESTION DE FACTURATION | F42: Socle de données | G42: TIPS | H42: Pointage soletanche bachis | I42: Interne | K42: Manuel
A43: =ROW()-3 -> 40 | B43: 46175 | C43: Reponsable Travaux | D43: Benjamin | E43: CIRCUIT DE VALIDATION | F43: Application métiers | G43: E-paraph | H43: Circuit de validation en interne avant signature | I43: Interne | K43: Manuel | N43: Tout
A44: =ROW()-3 -> 41 | B44: 46175 | C44: Reponsable Travaux | D44: Benjamin | E44: CIRCUIT DE VALIDATION | F44: Application métiers | G44: Pablo | H44: Juste validation | I44: Externe | K44: Manuel | N44: HARMONIE
A45: =ROW()-3 -> 42 | B45: 46175 | C45: Reponsable Travaux | D45: Benjamin | E45: GESTION DES CHANTIER | F45: Application métiers | G45: Excel | I45: Externe | J45: Microsoft | K45: Manuel | L45: Tous les jours | N45: Tout
A46: =ROW()-3 -> 43 | B46: 46175 | C46: Reponsable Travaux | D46: Benjamin | E46: GESTION IMPRÉVU CHANTIER | F46: Application métiers/Socle de donnée | G46: Quickconnect | H46: Constat contrat contradictoire, Fuite d'eau | I46: interne | K46: Manuel | N46: Tout
A47: =ROW()-3 -> 44 | B47: 46176 | C47: Comptabilité/gestion | D47: Sabine | E47: GESTION DE FACTURATION | F47: Application métiers/Socle de donnée | G47: Baseware | H47: Reception, harmoniser les champs des factures , contrôle, | I47: Interne | K47: Manuel | L47: Tous les jours | M47: Sabine , Martin, abdellah, PAMS | N47: Harmony | P47: En developpement | Q47: Rôle: Comptable fournisseur de chantier, centraliser, enregistrer les factures , rapprochement factures et reception(abdellah), respect de la loi LME => paiement des ADF / Facturation éléctronique
A48: =ROW()-3 -> 45 | B48: 46176 | C48: Comptabilité/gestion | D48: Sabine | E48: GESTION DE FACTURATION | F48: Socle de données | G48: Harmony | H48: Saisie des factures , extraction de litiges | I48: Interne | K48: Manuel | N48: Baseware
A49: =ROW()-3 -> 46 | B49: 46176 | C49: Comptabilité/gestion | D49: Sabine | E49: GESTION DE FACTURATION | F49: Application métiers | G49: Excel | H49: Chronofactures | I49: Externe | J49: Microsoft | K49: Manuel | N49: Tout
A50: =ROW()-3 -> 47 | B50: 46176 | C50: Comptabilité/gestion | D50: Sabine | E50: GESTION DE FACTURATION | F50: Socle de données | G50: Pablo | H50: Verification de montant de commande lors d'un différents | I50: Externe | K50: Manuel | N50: HARMONIE
A51: =ROW()-3 -> 48 | B51: 46177 | C51: Assistant RH | D51: Valerie | E51: ON BOARDING RH | F51: Socle de données | G51: E-checking | H51: Lutte contre le travail illégal , dépôt de document(visite médical…),Verification des autorisation, élaboration de badges apres test sécu ok | I51: Interne | K51: Manuel
A52: =ROW()-3 -> 49 | B52: 04/062026 | C52: Assistant RH | D52: Valerie | E52: GESTION DU PERSONNEL | F52: Socle de données | G52: Puma | H52: Prime de poste , heures de travail , compagnon BYT | I52: Interne | K52: Manuel | N52: BIP(chef de chantier qui deverse dans PUMA)
A53: =ROW()-3 -> 50 | B53: 04/062026 | C53: Assistant RH | D53: Valerie | E53: GESTION DU PERSONNEL | F53: Socle de données | G53: BIP /BAPS | H53: Intérim, heures , renouvellement, verification | I53: Interne | K53: Manuel | L53: Quotidien | M53: Valérie , agence d'intérim, | Q53: Agence d'itérim => 3 Juin
A54: =ROW()-3 -> 51 | B54: 04/062026 | C54: Assistant RH | D54: Valerie | E54: GESTION DU PERSONNEL | F54: Application métiers | G54: Excel | H54: Formations , repertorié suvi, coûts des formations, suivi des heures d'insertion, prime jalonné | I54: Externe | J54: Microsoft | K54: Manuel | L54: Quotidien
A55: =ROW()-3 -> 52 | B55: 04/062026 | C55: Assistant RH | D55: Valerie | E55: GESTION DES FORMATIONS | F55: Application métiers | G55: Pablo | H55: Bon de commande => formation | I55: Externe | K55: Manuel | L55: Hebdomadaire | N55: HARMONIE
A56: =ROW()-3 -> 53 | B56: 04/062026 | C56: Assistant RH | D56: Valerie | E56: GESTION DES FORMATIONS | F56: Application métiers | G56: BY MY SITE | H56: Logiciel de fomation, centralisation de formation | I56: Interne | K56: Manuel | L56: Hebdomadaire
A57: =ROW()-3 -> 54 | B57: 04/062026 | C57: Assistant RH | D57: Valerie | E57: GESTION DU PERSONNEL | F57: Application métiers | G57: H&R For you | H57: Demande de CP, monaitisation, placement gérance fonds, attestation employeur | I57: Interne | J57: BYCN | K57: Manuel | L57: Souvent | M57: Service RH
A58: =ROW()-3 -> 55 | B58: 46189 | C58: Ingé travaux | D58: Laurie | E58: AVANCEMENTS JALON CHANTIER | F58: Application métiers | G58: MS PROJECT | H58: Planning travaux, Objectif et tranferts transmis en amont aux ingé, relation humaines, chance, condtion, terrain, points de vigilance, pas beaucoup de prob technique | I58: Externe | K58: Manuel | Q58: Role : lien entre les méthode , le service achats , avec la maitrise pas de lien hierarchique, plannification anticiper les besoins gérer les allas , budgetisation, suivi global, mannager, gérer les sous traitant , vision + global que les conducteurs de travaux
A59: =ROW()-3 -> 56 | B59: 46189 | C59: Ingé travaux | D59: Laurie | G59: Excel | J59: Microsoft | K59: Manuel
A60: =ROW()-3 -> 57 | B60: 46189 | C60: Ingé travaux | D60: Laurie | E60: COMMANDE CHANTIER | F60: Socle de données | G60: Pablo | H60: commande de gros engins, nécéssite de faire des avenants, | K60: Manuel
A61: =ROW()-3 -> 58 | B61: 46189 | C61: Ingé travaux | D61: Laurie | E61: GESTION DES CONTRATS | F61: Application métiers | G61: Word | H61: Avenants, contrat | J61: Microsoft | K61: Manuel
A62: =ROW()-3 -> 59 | B62: 46189 | C62: Ingé travaux | D62: Laurie | E62: COMMANDE CHANTIER | F62: Socle de données | G62: Traktor | H62: Commande de gros engins | I62: Interne | K62: Manuel | M62: BYMAT | P62: En developpement (bug ,pas intuitif )
A63: =ROW()-3 -> 60 | B63: 46189 | C63: Ingé travaux | D63: r | E63: COMMANDE CHANTIER | F63: Application métiers | G63: ERP MAT | H63: Commande de coffrage , grue au tour, sécurite | I63: Interne | K63: Manuel | M63: BYMAT | N63: Inventaire via power bi | P63: En developpement (bug ,pas intuitif, )
A64: =ROW()-3 -> 61 | B64: 46189 | C64: Ingé travaux | D64: Laurie | E64: GESTION CHANTIER | F64: Socle de données | G64: Trimbleconnect | H64: Consultation des plans | K64: Manuel
A65: =ROW()-3 -> 62 | B65: 46189 | C65: Ingé travaux | D65: Laurie | E65: GESTION CHANTIER | F65: Socle de données | G65: Mezzoteam | H65: Suivi des plans, diffusion des plans | K65: Manuel/Automatique
A66: =ROW()-3 -> 63 | B66: 46189 | C66: Ingé travaux | D66: Laurie | E66: MAD | F66: Socle de données | G66: IDCAPTURE | H66: Utiliser pour les mises à dispositions | I66: Externe | K66: Manuel | L66: Par phase (sur fin de chantier
A67: =ROW()-3 -> 64 | B67: 46189 | C67: Ingé travaux | D67: Laurie | E67: GESTION CHANTIER | F67: Socle de données | G67: Quickconnect | H67: Fiche bêton , fiches feraillage , journaux chantier (pour les chef de chantier) | I67: Interne | K67: Manuel | P67: La technique les connexions
A68: =ROW()-3 -> 65 | B68: 46189 | C68: Ingé travaux | D68: Laurie | E68: AVANCEMENTS JALON CHANTIER | F68: Application métiers | G68: MMS | H68: Adhérence planning , évaluation/ appréciation des jalons | I68: Interne | K68: Manuel | Q68: A visé de reporting pour les gens du sièges
A69: =ROW()-3 -> 66 | B69: 46190 | C69: Direction | D69: Morgan | E69: AVANCEMENTS JALON CHANTIER | F69: Application métiers | G69: MIRO | H69: Récolter les obeya | K69: Manuel | M69: Par toute les équipes | Q69: Arret car prob de connexion
A70: =ROW()-3 -> 67 | B70: 46190 | C70: Direction | D70: Morgan | E70: AVANCEMENTS JALON CHANTIER | F70: Application métiers | G70: Excel | H70: Récolter les obeya, avanceement des travaux (tunnel); pointage de l'encadrement | K70: Manuel | M70: Par toute les équipes | Q70: A refaire le pointage de l'encadrement
A71: =ROW()-3 -> 68 | B71: 46190 | C71: Direction | D71: Morgan | E71: AVANCEMENTS JALON CHANTIER | F71: Application métiers | G71: Word | H71: Récolter les obeya | K71: Manuel | Q71: Prise de notes
A72: =ROW()-3 -> 69 | B72: 46190 | C72: Direction | D72: Morgan | E72: AVANCEMENTS JALON CHANTIER | F72: Application métiers | G72: POWER BI | H72: KPI | K72: Manuel
A73: =ROW()-3 -> 70 | B73: 46190 | C73: Direction | D73: Morgan | E73: AVANCEMENTS JALON CHANTIER | F73: Socle de données | G73: YELLOW | H73: KPI tunnel
A74: =ROW()-3 -> 71 | B74: 46190 | C74: Direction | D74: Morgan | E74: AVANCEMENTS JALON CHANTIER | F74: Application métiers | G74: MMS | H74: Identification des jalons , pointage | I74: Interne | K74: Manuel | L74: Hebdomadaire | Q74: Décupler via un excel
A75: =ROW()-3 -> 72 | B75: 46190 | C75: Direction | D75: Morgan | E75: GESTION TRAVAUX | F75: Application métiers | G75: Quickconnect | H75: visite sécurité, visite chantiers, toutes les visites | K75: Manuel | Q75: Manque de synchronisation; formulaire bug
A76: =ROW()-3 -> 73 | B76: 46175 | C76: Comptabilité/gestion | D76: Abdellah | E76: GESTION DE FACTURATION | F76: Socle de données | G76: Baseware | H76: Outils pour enregistrements, validation, partie circuit de validation, Engagé les litiges | I76: Interne | J76: Soletanche | K76: Manuel | L76: Quotidien | M76: Sabine, fournisseurs | N76: Harmonie | P76: Mature | Q76: Abdellah commence à engagé des dépenses, dans les bons ateliers
A77: =ROW()-3 -> 74 | B77: 46190 | C77: Direction | D77: Morgan | E77: CIRCUIT DE VALIDATION | F77: Application métiers | G77: E-paraph | H77: Circuit de validation en interne avant signature | K77: Manuel
A78: =ROW()-3 -> 75 | B78: 22/062026 | C78: Environnement | D78: Camille | E78: Contrôle Qualité /Environnement | F78: Application métiers/Socle de donnée | G78: Quickconnect | H78: 1/4h sensibilisation, suivi des consommatio(compteurs), suivi des prélevements, contrôle ste (traitement eau) | I78: Externe | K78: Manuel | L78: mensuel | M78: Beaucoup de service | N78: Powerbi | P78: WIP | Q78: Formulaire de visite environnement , demandé par camille pour le suivi des actions, jamais marché, mauvais connexion avec quikconnect dépendance de cet outils, concentration de demande sur les même personnes => pour être certifié => demande de bouygues,
A79: =ROW()-3 -> 76 | B79: 22/062026 | C79: Environnement | D79: Camille | E79: Contrôle Environnement | F79: Application métiers | G79: POWER BI | H79: Suivi des consommations (eau, éléctricité) | I79: Externe | K79: Manuel | L79: Jamais | Q79: Pas de réel compréhensions métier, outil pas bien conçu
A80: =ROW()-3 -> 77 | B80: 22/062026 | C80: Environnement | D80: Camille | E80: Contrôle Qualité | F80: Application métiers | G80: IDCAPTURE | H80: Faire la qualité | I80: Externe | K80: Manuel | L80: Quotidien | N80: Aucun | P80: En devellopement | Q80: Pas intuitif, prend pas en compte la 3d, trop de manip , pas possible de charger plein de fichier en momentané
A81: =ROW()-3 -> 78 | B81: 22/062026 | C81: Environnement | D81: Camille | G81: Trimbleconnect | H81: Première lecture, pouvoir localiser en 3d les éléments | I81: Externe | K81: Manuel | M81: DT | N81: Idcapture indirectement par des screenshot en 3d | P81: Mature | Q81: Mis en place d'un outil de réserve mêlant 3D , identification des sujet bloquant pour les MaD
A82: =ROW()-3 -> 79 | B82: 22/062026 | C82: Environnement | D82: Camille | G82: Liveobject(ORANGE) | H82: Renvoie de les indicateurs de consommation sur les compteurs de pompage | I82: Externe | K82: Automatique | L82: Mensuel | M82: Automatique | N82: Export manuel des pulsations pour les réinjecter dasn des tab internes | O82: Plateforme d'ORANGE | P82: Mature
A83: =ROW()-3 -> 80 | B83: 22/062026 | C83: Environnement | D83: Camille | G83: Sixsense monitoring | H83: Accoustique, sonomètre | I83: Externe | K83: Automatique | L83: Tous les jours( en phase creusement) , mensuellement en phase final | M83: Automatique | N83: Ponctuellement en fonction des demandes | P83: Mature | Q83: Dossie rbruit fait en amont du_chantier , outil permettant de "protéger " Bouygues et de justifier du respect
A84: =ROW()-3 -> 81 | B84: 22/062026 | C84: Environnement | D84: Camille | G84: Wastemarket place (wakio) | H84: Gestion des déchets | I84: Externe | K84: Manuel | L84: Quotidien | M84: Tous les chefs de chantier | N84: Avant POWER BI, | P84: Mature (quelques ysfonctionnement dû à l'humain) | Q84: Obligation légal de suivre les déchets dangereux ( pouvant porté atteinte à l'envi, huma; Traduis un besoin du client => MO => 100% de la traçabilité de tous les déchets dangereux)
A85: =ROW()-3 -> 82 | B85: 22/062026 | C85: Environnement | D85: Camille | G85: Lafarge + | H85: SUIVI bl, m3 coulé | I85: Externe | K85: Automatique | L85: Quotidien | M85: Lafarge | N85: Aucun | O85: Application | P85: Mature | Q85: Utiliser depuis 2026
A86: =ROW()-3 -> 83 | B86: 22/062026 | C86: Environnement | D86: Camille | G86: Lucee TP | H86: Déterminer les espèces envahissantes | I86: Externe | K86: Manuel | L86: Ponctuellement | Q86: amélioration : outil permettant de cartographie ; obligation de veiller à ne pas propager le dev des espèces envahissantes
A87: =ROW()-3 -> 84 | B87: 22/062026 | C87: Environnement | D87: Camille | G87: Power Point | H87: Déclaration de HIPO | I87: Externe | K87: Manuel
A88: =ROW()-3 -> 85 | B88: 22/062026 | C88: TOPO | D88: Franck | G88: Autocad | H88: Tracer de ligne, nettoyage des plans | K88: Manuel | L88: Quotidien | M88: La topo | N88: Covadis | O88: Licence réseau | P88: Mature | Q88: Récupère les plans de coffrage, intermédiaire entre la dt et le terrain , implantations(plus en début de chantier)
A89: =ROW()-3 -> 86 | B89: 22/062026 | C89: TOPO | D89: Franck | G89: Cyclone 3dr | H89: Générer des points topo, analyse des scans , retraitementement de nuage de point | K89: Retraitement automatique du nettoyage des plans, Alimenter manuellement | L89: Quotidien | M89: La topo | N89: Non | O89: Licence | P89: Mature | Q89: Scan réalisé par un scanner pharo
A90: =ROW()-3 -> 87 | B90: 22/062026 | C90: TOPO | D90: Franck | G90: La scene | H90: Assemblage de position de scan | J90: Leica | K90: Manuel | L90: Hebdomadaire | M90: Topo | N90: cyclone 3d
A91: =ROW()-3 -> 88 | B91: 22/062026 | C91: TOPO | D91: Franck | G91: Covadis | H91: Genration des points de topo | K91: Manuel | L91: Quotidien | M91: Topo
A92: =ROW()-3 -> 89 | B92: 22/062026 | C92: TOPO | D92: Franck | G92: Trimbleconnect | H92: Récupère les plans, outils de partage des plans | K92: Manuel | L92: Quotidien | M92: Topo | N92: cyclone 3d, Autocad
A93: =ROW()-3 -> 90 | B93: 22/062026 | C93: TOPO | D93: Franck | G93: Excel | H93: Rapport,avec des plans de cyclone 3d
A94: =ROW()-3 -> 91 | B94: 22/062026 | C94: TOPO | D94: Franck | G94: Pixis | H94: Guidage du tunnelier, | K94: Automatique | L94: Quotidien | M94: Equipe tunnel, Topo, Automatiquement | N94: pixys tool(rapport de lever d'anneau, position machine) , mobidic
A95: =ROW()-3 -> 92 | B95: 22/062026 | C95: TUNNEL | D95: SALLY | G95: Autocad | H95: Modification des plans, faire des schéma | I95: Externe | K95: Manuel | L95: Quotidien | M95: DT
A96: =ROW()-3 -> 93 | B96: 22/062026 | C96: TUNNEL | D96: SALLY | G96: Trimbleconnect | H96: Visualisation 3D | I96: Externe | K96: Manuel | L96: Hebdomadaire | M96: DT
A97: =ROW()-3 -> 94 | B97: 22/062026 | C97: TUNNEL | D97: SALLY | G97: MS PROJECT | H97: Planning | I97: Interne | K97: Manuel | L97: rarement | M97: Sally
A98: =ROW()-3 -> 95 | B98: 22/062026 | C98: TUNNEL | D98: SALLY | G98: YELLOW | H98: Suivi l'avancement du tunnnelier , info en temps réel , | I98: Interne | K98: Automatique | L98: Quotidien | M98: Automatique
A99: =ROW()-3 -> 96 | B99: 22/062026 | C99: TUNNEL | D99: SALLY | G99: Excel | H99: Planning, tableau de suivi, | I99: Externe | K99: Manuel | L99: Quotidien | M99: Equpe Tunnel | Q99: Suivi de production pouvant être automatisé
A100: =ROW()-3 -> 97 | B100: 22/062026 | C100: TUNNEL | D100: SALLY | G100: Quickconnect | H100: Suivi béton, journaux de chantiers, réception de livraison des voussoir, rec mortier | I100: Interne | K100: Manuel | L100: Quotidien | M100: Equpe Tunnel | N100: Power BI
A101: =ROW()-3 -> 98 | B101: 22/062026 | C101: TUNNEL | D101: SALLY | G101: IDCAPTURE | H101: Pour les finitions, communication avec la maitrise d'œuvre | I101: Interne | K101: Manuel | L101: Quotidien | M101: Equpe Tunnel
...

Sheet 📝 Guide Entretien
A1: GUIDE D'ENTRETIEN – CARTOGRAPHIE OUTILS IT CHANTIER
A2: 🔑 = Question prioritaire à ne pas manquer
A3: INTRODUCTION
A4: Présentation | B4: Bonjour, je suis [prénom], stagiaire CFI au sein de Bouygues Construction. Cartographie des outils IT utilisés sur le chantier afin d'en avoir une vision globale + interconnexions. | C4: Durée estimée : 30-45 min
A5: IDENTIFICATION
A6: Q1 | B6: 🔑 Quels outils / logiciels utilisez-vous au quotidien dans votre activité ? | C6: Lister tous les outils
A7: Q2 | B7: Depuis combien de temps utilisez-vous cet outil ? | C7: Date de mise en place
A8: USAGE
A9: Q3 | B9: 🔑 À quoi vous sert cet outil concrètement ? Quelle est son utilité principale ? | C9: Comprendre le cas d'usage métier
A10: Q4 | B10: Combien de personnes l'utilisent dans votre équipe / sur le chantier ? | C10: Volumétrie utilisateurs
A11: TECHNIQUE
A12: Q5 | B12: 🔑 Est-ce un outil développé en interne par Bouygues ou fourni par un éditeur externe ? | C12: Interne / Externe
A13: Q6 | B13: L'outil est-il hébergé en local ou dans le cloud ? | C13: Architecture technique
A14: ALIMENTATION DES DONNÉES
A15: Q7 | B15: 🔑 Comment les données sont-elles saisies dans l'outil ? Manuellement ou automatiquement ? | C15: Mode d'alimentation
A16: Q8 | B16: 🔑 Qui saisit / alimente les données ? Quel profil ? | C16: Responsable alimentation
A17: Q9 | B17: 🔑 À quelle fréquence les données sont-elles mises à jour ? | C17: Quotidien / hebdo / mensuel...
A18: INTERCONNEXIONS
A19: Q10 | B19: 🔑 Cet outil reçoit-il des données d'un autre outil ? Lequel ? | C19: Flux entrants
A20: Q11 | B20: 🔑 Cet outil envoie-t-il des données vers un autre outil ? Lequel ? | C20: Flux sortants
A21: Q12 | B21: Y a-t-il des exports réguliers (Excel, PDF, API...) ? Vers qui ? | C21: Format des échanges
A22: ÉVALUATION
A23: Q13 | B23: Êtes-vous satisfait de cet outil ? Quels sont ses points forts ? | C23: Satisfaction
A24: Q14 | B24: Quels sont les problèmes rencontrés ou les manques ? | C24: Points faibles / Risques
A25: Q15 | B25: Avez-vous des évolutions ou remplacements prévus ? | C25: Roadmap
A26: CLÔTURE
A27: Conclusion | B27: Y a-t-il d'autres outils que vous utilisez et que nous n'avons pas abordés ? Avez-vous des collègues à qui je devrais parler ? | C27: Identifier d'autres interlocuteurs

Sheet 📊 Tableau de Bord
A1: TABLEAU DE BORD – AVANCEMENT CARTOGRAPHIE
A3: Indicateur | B3: Valeur | C3: Source | H3: {=_xlfn.UNIQUE('📋 Collecte Entretiens'!D4:D93)} -> Julie | I3: {=_xlfn._xlws.SORT(_xlfn.UNIQUE('📋 Collecte Entretiens'!G4:G94,FALSE,FALSE))} -> Anaconda | J3: =INDEX('📋 Collecte Entretiens'!K4:K94,MATCH('📊 Tableau de Bord'!I3,'📋 Collecte Entretiens'!G4:G94,0)) -> Manuel
A4: Nb entretiens réalisés | B4: ='📋 Collecte Entretiens'!D103 -> 16 | C4: Feuille Collecte | H4: Alexandre | I4: Autocad
A5: Nb outils identifiés | B5: ='📋 Collecte Entretiens'!G103 -> 51 | C5: Feuille Collecte | H5: Alexandre | I5: Baseware
A6: Nb outils internes | B6: =COUNTIF('📋 Collecte Entretiens'!I4:I103,"Interne") -> 13 | C6: Feuille Collecte | H6: Etienne | I6: BATIS
A7: Nb outils externes | B7: =COUNTIF('📋 Collecte Entretiens'!I4:I103,"Externe") -> 47 | C7: Feuille Collecte | H7: Martin | I7: BIM vision
A8: Nb outils alimentation manuelle | B8: =COUNTIF('📋 Collecte Entretiens'!K4:K103,"Manuel") -> 84 | C8: Feuille Collecte | H8: Thierry | I8: BIP /BAPS
A9: Nb outils alimentation automatique | B9: =COUNTIF('📋 Collecte Entretiens'!K4:K103,"Automatique") -> 9 | C9: Feuille Collecte | H9: Thierry | I9: BY MY SITE
H10: Morgan | I10: Cabine de pilotage(Power BI)
H11: Abdellah | I11: Civil 3D
H12: Benjamin | I12: Covadis
H13: Sabine | I13: CWT
H14: Valerie | I14: Cyclone 3dr
H15: Laurie | I15: Docusign
H16: r | I16: E-checking
H17: Camille | I17: E-paraph
H18: Franck | I18: E-project
I19: ERP MAT
I20: Excel
I21: H&R For you
I22: Harmony
I23: IDCAPTURE
I24: Inventor
I25: La scene
I26: Lafarge +
I27: Liveobject(ORANGE)
I28: Lucee TP
I29: Mezzoteam
I30: MIRO
... I59: Achat +(achat pablo => opérationnel)
I60: Neoacces | J60: créer les badges => gère les accès

Sheet 🔍 Fiche Outil Détaillée
A1: FICHE DÉTAILLÉE – OUTIL IT
A2: IDENTIFICATION
A3: Nom de l'outil
A4: Éditeur / Fournisseur
A5: Version
A6: Site web / Documentation
A7: USAGE
A8: Fonction principale
A9: Service(s) utilisateur(s)
A10: Nombre d'utilisateurs
A11: Contexte d'utilisation
A12: TECHNIQUE
... A28: Commentaires libres
